fractaly/__init__.py
fractaly/core1.py
fractaly/py.typed
fractaly/_internal/__init__.py
fractaly/_internal/core2.py
fractaly/lib/linux64/libfractal_maths.so
fractaly/lib/win64/fractal_maths.dll
fractaly/src/test_fractal_maths.py
fractaly-1.0.0.dist-info/METADATA
fractaly-1.0.0.dist-info/WHEEL
fractaly-1.0.0.dist-info/top_level.txt
fractaly-1.0.0.dist-info/RECORD
