Metadata-Version: 2.4
Name: fractaly
Version: 1.0.0
Summary: A package for fractal creation and display them
Home-page: https://github.com/masoud-najafi/fractaly-project
Author: Masoud NAJAFI
Author-email: Masoud NAJAFI <your.email@example.com>
Project-URL: Homepage, https://github.com/masoud-najafi/fractaly-project
Project-URL: Documentation, https://docs.example.com
Project-URL: Repository, https://github.com/masoud-najafi/fractaly-project
Classifier: Programming Language :: Python :: 3
Classifier: Operating System :: OS Independent
Classifier: Typing :: Typed
Requires-Python: >=3.7
Dynamic: author
Dynamic: home-page
Dynamic: requires-python
